[{"id":2,"title":"Veracruz","content":"Safeway Inc."},
{"id":2,"title":"PT Cruiser","content":"Nelco Laboratories, Inc."},
{"id":3,"title":"Legacy","content":"ALK-Abello, Inc."},
{"id":3,"title":"5000CS","content":"Pfizer Laboratories Div Pfizer Inc"},
{"id":2,"title":"Continental","content":"Provision Medical"},
{"id":3,"title":"3 Series","content":"Dispensing Solutions, Inc."},
{"id":2,"title":"Reatta","content":"Preferred Pharmaceuticals, Inc."},
{"id":5,"title":"CL","content":"Libertas Pharma, Inc."},
{"id":5,"title":"Impreza","content":"KMART CORPORATION"},
{"id":3,"title":"Axiom","content":"Hospira, Inc."},
{"id":3,"title":"Silverado","content":"The Magni Company"},
{"id":2,"title":"Discovery","content":"King Bio Inc."},
{"id":2,"title":"Pilot","content":"PD-Rx Pharmaceuticals, Inc."},
{"id":3,"title":"Outback","content":"VersaPharm Incorporated"},
{"id":3,"title":"9-5","content":"Bath & Body Works, Inc."},
{"id":2,"title":"G37","content":"Dynarex Corporation"},
{"id":3,"title":"Ranger","content":"McKesson"},
{"id":2,"title":"M6","content":"Apotheca Company"},
{"id":3,"title":"Hearse","content":"Georgia-Pacific Consumer Products LP"},
{"id":3,"title":"Suburban 3500","content":"Physicians Total Care, Inc."},
{"id":3,"title":"Phantom","content":"Contract Pharmacy Services-PA"},
{"id":3,"title":"Sentra","content":"IVC Industries, Inc. dba Inverness Medical Nutritionals Group"},
{"id":3,"title":"Laser","content":"Lancaster S.A.M."},
{"id":3,"title":"Q","content":"Colgate Oral Pharmaceuticals, Inc."},
{"id":2,"title":"Lancer","content":"Virtus Pharmaceuticals"},
{"id":5,"title":"del Sol","content":"Merck Sharp & Dohme Corp."},
{"id":3,"title":"Ram","content":"Hospira, Inc."},
{"id":5,"title":"NV2500","content":"DOLGENCORP, INC."},
{"id":5,"title":"Firefly","content":"Sandoz Inc"},
{"id":2,"title":"Monte Carlo","content":"PHARMAZEUTISCHE FABRIK DR. RECKEWEG & CO"},
{"id":5,"title":"2500 Club Coupe","content":"TAYLOR JAMES, LTD."},
{"id":3,"title":"M6","content":"DIRECT RX"},
{"id":2,"title":"Santa Fe","content":"Upsher-Smith Laboratories, Inc."},
{"id":5,"title":"LS","content":"Amarin Pharma Inc."},
{"id":2,"title":"Reno","content":"Meijer Distribution Inc"},
{"id":5,"title":"MX-5","content":"Uriel Pharmacy Inc."},
{"id":3,"title":"RAV5","content":"Pharmacia and Upjohn Company"},
{"id":5,"title":"Topaz","content":"Par Pharmaceutical, Inc."},
{"id":3,"title":"RS 5","content":"AIRGAS NOR PAC INC"},
{"id":2,"title":"Impreza","content":"Preferred Pharmaceuticals, Inc"},
{"id":2,"title":"Pathfinder","content":"7-Eleven"},
{"id":3,"title":"Sunfire","content":"Ventura Corporation LTD"},
{"id":3,"title":"Ram Van 3500","content":"Mary Kay Inc."},
{"id":3,"title":"Galant","content":"Uriel Pharmacy Inc."},
{"id":2,"title":"Carens","content":"Laboratorios Dr. Collado, C x A."},
{"id":3,"title":"300","content":"Publix Super Markets Inc"},
{"id":2,"title":"F350","content":"GlaxoSmithKline Consumer Healthcare LP"},
{"id":5,"title":"XL-7","content":"Guna spa"},
{"id":3,"title":"Firebird","content":"King Bio Inc."},
{"id":3,"title":"M5","content":"Innovation Specialties"},
{"id":3,"title":"X-Type","content":"Washington Homeopathic Products"},
{"id":3,"title":"Aviator","content":"Kareway Product, Inc."},
{"id":3,"title":"RX-8","content":"KGP Products, Inc. (dba PREMIER)"},
{"id":5,"title":"Canyon","content":"Western Family Foods Inc"},
{"id":5,"title":"Mariner","content":"Allergy Laboratories, Inc."},
{"id":3,"title":"E-Class","content":"UCB, Inc."},
{"id":3,"title":"Expedition","content":"Accra-Pac, Inc."},
{"id":3,"title":"F350","content":"Ventura Corporation LTD."},
{"id":3,"title":"H2","content":"ProPhase Labs, Inc."},
{"id":2,"title":"Bravada","content":"Jafra Cosmetics International Inc"},
{"id":5,"title":"F350","content":"Homeocare Laboratories"},
{"id":2,"title":"Savana 3500","content":"Hannaford Brothers Company"},
{"id":3,"title":"7 Series","content":"Cobalt Laboratories Inc."},
{"id":3,"title":"Concorde","content":"Taro Pharmaceutical Industries Ltd."},
{"id":2,"title":"E-Series","content":"Unit Dose Services"},
{"id":2,"title":"850","content":"Lannett Company, Inc."},
{"id":3,"title":"RAV5","content":"Maximum Results Solution, Inc."},
{"id":5,"title":"MPV","content":"Aidarex Pharmaceuticals LLC"},
{"id":5,"title":"Range Rover Sport","content":"Cardinal Health"},
{"id":5,"title":"Sunfire","content":"Topco Associates LLC"},
{"id":3,"title":"E-Class","content":"sanofi-aventis U.S. LLC"},
{"id":3,"title":"Pajero","content":"McKesson Contract Packaging"},
{"id":3,"title":"RVR","content":"Personal Care Products, Inc"},
{"id":3,"title":"G35","content":"Allermed Laboratories, Inc."},
{"id":2,"title":"Rainier","content":"Medical Products Laboratories, Inc."},
{"id":2,"title":"Yukon XL 3500","content":"Baxter Healthcare Corporation"},
{"id":2,"title":"Prelude","content":"Antigen Laboratories, Inc."},
{"id":3,"title":"E-Series","content":"Hannaford Brothers Company"},
{"id":2,"title":"M5","content":"Physicians Total Care, Inc."},
{"id":3,"title":"Grand Prix","content":"Clinical Solutions Wholesale"},
{"id":2,"title":"F-350 Super Duty","content":"DIRECT RX"},
{"id":3,"title":"Escalade EXT","content":"Sun Products Corporation"},
{"id":3,"title":"Scoupe","content":"Macleods Pharmaceuticals Limited"},
{"id":5,"title":"200","content":"Parfums Christian Dior"},
{"id":3,"title":"Escape","content":"Indiana Botanic Gardens"},
{"id":3,"title":"Express 2500","content":"Mary Kay Inc."},
{"id":5,"title":"Marauder","content":"Teva Pharmaceuticals USA Inc"},
{"id":5,"title":"B-Series","content":"Antigen Laboratories, Inc."},
{"id":3,"title":"Vantage","content":"Sun Pharma Global FZE"},
{"id":2,"title":"Escort","content":"Ionx Holdings d/b/a HelloLife Inc."},
{"id":5,"title":"Titan","content":"Nelco Laboratories, Inc."},
{"id":2,"title":"Legacy","content":"Cargo Cosmetics Corp."},
{"id":2,"title":"3500 Club Coupe","content":"HEB"},
{"id":3,"title":"GT","content":"HARTMAN BROTHERS, INC"},
{"id":3,"title":"Golf","content":"Eon Labs, Inc."},
{"id":3,"title":"FR-S","content":"Deseret Biologicals, Inc."},
{"id":3,"title":"Acadia","content":"AvKARE, Inc."},
{"id":5,"title":"Sonata","content":"Reckitt Benckiser LLC"},
{"id":3,"title":"S5","content":"Xiamen Anna Global Co., Ltd"},
{"id":2,"title":"Millenia","content":"Zila Therapeutics, Inc."}]